radianceQuantifier/__init__.py
radianceQuantifier/__main__.py
radianceQuantifier/radianceQuantifierLogo.png
radianceQuantifier/dataprocessing/__init__.py
radianceQuantifier/dataprocessing/inVivoRadianceImagePlotting.py
radianceQuantifier/dataprocessing/inVivoRadianceProcessing.py
radianceQuantifier/dataprocessing/miscFunctions.py
radianceQuantifier/dataprocessing/modelingFunctions.py
radianceQuantifier/dataprocessing/newInVivoRadianceProcessing.py
radianceQuantifier/dataprocessing/oldinVivoRadianceProcessing.py
radianceQuantifier/dataprocessing/survivalProcessing.py
radianceQuantifier/plotting/__init__.py
radianceQuantifier/plotting/facetPlot1D.py
radianceQuantifier/plotting/facetPlot2D.py
radianceQuantifier/plotting/facetPlot3D.py
radianceQuantifier/plotting/facetPlotCategorical.py
radianceQuantifier/plotting/facetPlotLibrary.py
radianceQuantifier/plotting/interactiveGUIElements.py
radianceQuantifier/plotting/plottingFunctions.py
radianceQuantifier/plotting/plottingGUI.py
radianceQuantifier/setup/__init__.py
radianceQuantifier/setup/experimentCreationGUI.py
radianceQuantifier/setup/experimentSetupGUI.py
radianceQuantifier/setup/modelExperimentGUI.py
radianceQuantifier/setup/processExperimentGUI.py
radianceQuantifier/setup/radianceRegionSelectionGUI.py
radianceQuantifier/setup/removeExperiment.py
radianceQuantifier-0.8.0.dist-info/LICENSE.txt
radianceQuantifier-0.8.0.dist-info/METADATA
radianceQuantifier-0.8.0.dist-info/WHEEL
radianceQuantifier-0.8.0.dist-info/entry_points.txt
radianceQuantifier-0.8.0.dist-info/top_level.txt
radianceQuantifier-0.8.0.dist-info/RECORD
