Metadata-Version: 2.1
Name: radianceQuantifier
Version: 0.8.0
Summary: Automatically crops mice and quantifies their tumor luminescences from raw IVIS images
Home-page: https://github.com/soorajachar/radianceQuantifier
Author: Sooraj Achar
Author-email: acharsr@nih.gov
Classifier: Programming Language :: Python :: 3
Classifier: License :: OSI Approved :: GNU General Public License v3 (GPLv3)
Classifier: Operating System :: Unix
Classifier: Operating System :: MacOS :: MacOS X
Classifier: Operating System :: Microsoft :: Windows
Classifier: Intended Audience :: Science/Research
License-File: LICENSE.txt
Requires-Dist: joblib >=1.1.0
Requires-Dist: numpy >=1.21.1
Requires-Dist: opencv-python
Requires-Dist: colorcet
Requires-Dist: hdbscan
Requires-Dist: scipy
Requires-Dist: tqdm
Requires-Dist: pandas
Requires-Dist: pytesseract
Requires-Dist: matplotlib >=3.3.0
Requires-Dist: seaborn >=0.11.1
Requires-Dist: Pillow
Requires-Dist: plateypus
Requires-Dist: scikit-learn
Requires-Dist: kneed
Requires-Dist: lmfit
Requires-Dist: pickle5
